{
  "planning": {
    "Lundi": {
      "planning": [],
      "date": "04/03"
    },
    "Mardi": {
      "planning": [],
      "date": "05/03"
    },
    "Mercredi": {
      "planning": [],
      "date": "06/03"
    },
    "Jeudi": {
      "planning": [],
      "date": "07/03"
    },
    "Vendredi": {
      "planning": [],
      "date": "08/03"
    },
    "Samedi": {
      "planning": [],
      "date": "09/03"
    },
    "Dimanche": {
      "planning": [],
      "date": "10/03"
    }
  },
  "weekDates": {
    "startOfWeekDate": "04/03",
    "endOfWeekDate": "10/03"
  },
  "weekNumber": "10"
}